{"404.md":"c675e376","animation-controllers_afk-animation-controller.md":"d8962e5a","animation-controllers_animation-controllers-intro.md":"c7ca31c8","animation-controllers_death-commands.md":"d0afd6e9","animation-controllers_entity-commands.md":"a11ca670","animation-controllers_index.md":"7f3b67a2","animation-controllers_molang-into-scoreboard.md":"9bdde85b","animation-controllers_respawn-commands.md":"f1becbd6","blocks_applying-effects.md":"ec992458","blocks_block-materials.md":"08669bb8","blocks_block-shapes.md":"dacf453e","blocks_block-sounds.md":"a4ba8a9c","blocks_block-tags.md":"d8e42bc2","blocks_block-texture-variation.md":"d4d7ae4d","blocks_blocks-16.md":"73d5a64f","blocks_blocks-intro.md":"9268ee11","blocks_custom-crops.md":"e6bc5ac3","blocks_custom-fluids.md":"e248c051","blocks_custom-glass-blocks.md":"bda24f52","blocks_custom-tree.md":"bf46a2f3","blocks_fake-blocks.md":"e1f9ec51","blocks_flipbook-textures.md":"877d5538","blocks_head-like-rotation.md":"f24a45bf","blocks_index.md":"961e1ae3","blocks_legacy-block-tags.md":"d0545182","blocks_ore-loot-tables.md":"c6124428","blocks_rotatable-blocks.md":"51dd8270","blocks_troubleshooting-blocks.md":"d8b32b3d","commands_block-states.md":"44b9c8dd","commands_entity-counter.md":"ff9031a2","commands_index.md":"cba2a381","commands_intro-to-command-blocks.md":"31c9b140","commands_mcfunctions.md":"fe31e0f9","commands_nbt-commands.md":"c3c79d6d","commands_new-execute.md":"ae660d1b","commands_on-first-join.md":"2035a352","commands_on-player-death.md":"3d991bc6","commands_on-player-join.md":"84112668","commands_on-player-leave.md":"d41f2f6f","commands_on-player-respawn.md":"2588224e","commands_relative-coordinates.md":"0e792d61","commands_scoreboard-operations.md":"f3e6a3bd","commands_scoreboard-timers.md":"efd994ba","commands_selectors.md":"37084782","commands_tellraw.md":"b1ab1e5d","concepts_contents.md":"fb42e3ca","concepts_emojis.md":"f03a2e5a","concepts_index.md":"2714a513","concepts_molang.md":"d11788ab","concepts_namespaces.md":"1c31a45d","concepts_overwriting-assets.md":"972cd6ec","concepts_shaders.md":"d66c50fc","concepts_sounds.md":"397e681d","concepts_subpacks.md":"08978c25","concepts_text-and-translations.md":"236e4fe7","concepts_textures-list.md":"a5252077","contribute-how-to.md":"6439a52f","contribute-style.md":"a83db5ed","contribute.md":"a7be1a02","discord.md":"15e90aea","documentation_advanced-molang.md":"10d1220c","documentation_creative-categories.md":"60fc31a9","documentation_fog-ids.md":"f8eebdfe","documentation_index.md":"89caf2bb","documentation_material-config-description.md":"1933fc1c","documentation_materials.md":"a0a478a8","documentation_pack-structure.md":"4c98d151","documentation_projectiles.md":"c8b08d3f","documentation_queries.md":"5544d45c","documentation_shared-constructs.md":"9df65c52","documentation_sound-definitions.md":"09fbb4d2","entities_boat-entities.md":"4c017d10","entities_detecting-other-entities.md":"fe1f73a5","entities_disabling-team-damage.md":"e3b3e1e0","entities_dummy-components.md":"02bf1e4e","entities_dummy-entities.md":"75dc0b0c","entities_entity-attack.md":"8bc28593","entities_entity-events.md":"55b005da","entities_entity-holds-item.md":"7650ff5c","entities_entity-intro-bp.md":"10124c23","entities_entity-intro-rp.md":"493986c6","entities_entity-movement.md":"dd2c32cd","entities_entity-properties.md":"65042eb2","entities_flying-entities.md":"2816bdb1","entities_index.md":"a7c9ab5e","entities_introduction-to-aec.md":"38f048a5","entities_invulnerable-entities.md":"206c3e50","entities_look-at-entity.md":"52cb5206","entities_non-mob-runtime-identifiers.md":"c18b9128","entities_npc-dialogs.md":"01cd02d3","entities_render-controllers.md":"b0bec4e1","entities_runtime-identifier.md":"3d6490b6","entities_sleeping-entities.md":"fa93c60a","entities_solid-entities.md":"502fb414","entities_spawn-rules.md":"bdcb5038","entities_spawning-tamed-entities.md":"2124dfd4","entities_timers.md":"cfa80bff","entities_troubleshooting-entities.md":"afc52e8a","entities_vanilla-usage-components.md":"fb93ce17","entities_vanilla-usage-spawn-rules.md":"204ab72c","entities_village-mechanic.md":"d36e3162","entities_vuc-full.md":"360f5033","entities_vusr-full.md":"b5cfb9be","graph-test.md":"729a6561","guide_addons.md":"ee5df0b1","guide_advancedmanifest.md":"6f611a88","guide_blockbench.md":"2cf5f41a","guide_custom-entity.md":"92d6cbe6","guide_custom-item.md":"41cbbf54","guide_download-packs.md":"c4be190a","guide_format-version.md":"bd43d062","guide_index.md":"032674e4","guide_introduction.md":"55d48786","guide_loot-table.md":"176e132e","guide_project-setup-android.md":"368c89f8","guide_project-setup.md":"dbc4e3d9","guide_software-preparation.md":"4e2691e9","guide_troubleshooting.md":"217aa89c","guide_understanding-json.md":"1dd490d5","hacktoberfest.md":"c6ddb828","index.md":"2dd471be","items_attachables.md":"9e562ea7","items_custom-armor.md":"a5589464","items_custom-weapon.md":"dcc24886","items_enchantments.md":"11cd98e4","items_equipped-item-commands.md":"0978b1cd","items_index.md":"e81cd7d9","items_item-identifiers.md":"52e3790f","items_items-16.md":"28d4953f","items_items-intro.md":"2ccbb4cb","items_spawning-items.md":"fef1eb68","items_spear.md":"0a8c7ad2","items_throwable.md":"4814120c","items_tool-durability.md":"5ff563cd","items_troubleshooting-items.md":"a3dca8ca","items_vanilla-usage-items.md":"11ad96df","items_vui-full.md":"4e015055","json-ui_add-hud-elements.md":"00376fc3","json-ui_aseprite-animations.md":"44d2fab8","json-ui_best-practices.md":"79d4527b","json-ui_index.md":"b02a42f0","json-ui_json-ui-documentation.md":"bf04dcdc","json-ui_json-ui-intro.md":"ce6c498a","json-ui_preserve-title-texts.md":"be729021","json-ui_string-to-number.md":"0dc4f666","loot_index.md":"e57a6eea","loot_item-functions.md":"405f943d","loot_loot-tables.md":"82c9b37e","loot_randomized-structure-loot.md":"8026bf72","loot_recipes.md":"1f67b106","loot_trade-tables.md":"d5ade70e","loot_trading-behavior.md":"fcaa9b3b","meta_addon-performance.md":"1c6dedab","meta_index.md":"0b026123","meta_jq.md":"611f0f71","meta_style-guide.md":"fc2cdbdb","meta_useful-links.md":"3868b86a","meta_using-schemas.md":"9fa59efc","meta_version-control.md":"d594eb3c","nbt_experimental-education-edition.md":"868812b3","nbt_index.md":"6f96368f","nbt_mcstructure.md":"e88f2d86","nbt_nbt-in-depth.md":"2dba1258","nbt_step-by-step-example.md":"66412b1e","nbt_structure-limits.md":"293131c4","particles_disabling-particles.md":"dc18d978","particles_index.md":"a4504626","particles_particles-and-sounds.md":"01696f06","particles_particles.md":"55dfe8a2","particles_vanilla-particles.md":"4619778f","privacy.md":"03a0c503","scripting_api-environment.md":"d3e971f6","scripting_custom-command.md":"f1cf5364","scripting_game-tests.md":"faf0acb3","scripting_gametest-form.md":"15c20914","scripting_gametest-qna.md":"3a1ac875","scripting_index.md":"2dc377cd","scripting_resources.md":"84391675","scripting_saving-loading.md":"0f48e4ca","scripting_script-net.md":"05a45ace","scripting_script-server.md":"060bd18d","scripting_script-watchdog.md":"533eb4db","scripting_scripting-intro.md":"5a514caf","scripting_starting-scripts.md":"5bfca921","scripting_troubleshooting.md":"a7433ed3","scripting_typescript.md":"7c28d58e","scripting_what-is-script.md":"ae4b0de1","servers_index.md":"cb210c53","servers_raknet-and-mcpe.md":"6c369d95","servers_server-software.md":"d8b3cb99","test.md":"f575ab7b","visuals_animated-entity-texture.md":"3128a902","visuals_animation-effects.md":"dba67346","visuals_bedrock-modeling.md":"26f64b6d","visuals_custom-skin-packs.md":"9c1f0d98","visuals_death-animations.md":"09485940","visuals_glowing-texture.md":"186019d4","visuals_index.md":"55f4b6cf","visuals_introduction.md":"bba14aae","visuals_leash-position.md":"9deaef57","visuals_materials.md":"cca6a948","visuals_math-based-animations.md":"4feee3e4","visuals_player-geometry.md":"e610df34","visuals_remove-shadows.md":"337a89b8","visuals_retexturing-spawn-eggs.md":"2d2a68fc","visuals_structure-presentation.md":"2c03b334","vr_editing-your-first-model.md":"761678de","vr_index.md":"60655c71","vr_installing-bedrock-vr.md":"0e19a115","vr_pack_setup.md":"97de0b56","world-generation_biome-tags.md":"11d32079","world-generation_biomes.md":"9a32d374","world-generation_custom-ores.md":"90a0a708","world-generation_feature-block-conditions.md":"35c5e5b7","world-generation_feature-types.md":"39e6e1d4","world-generation_heightmap-noise.md":"1982eaeb","world-generation_index.md":"256d10c7","world-generation_structure-features.md":"324df788","world-generation_surface-builder.md":"b5636ac0","world-generation_world-generation-intro.md":"03731109"}
